{
  "id": "HALO-13",
  "title": "Setup pytest and test directory structure",
  "type": "task",
  "status": "closed",
  "priority": 2,
  "description": "Create test framework structure with pytest.\n\n## Structure\n```\ntests/\n\u251c\u2500\u2500 unit/\n\u2502   \u251c\u2500\u2500 test_classify_spend.py\n\u2502   \u251c\u2500\u2500 test_analyze_agent.py\n\u2502   \u2514\u2500\u2500 test_recommend_logic.py\n\u251c\u2500\u2500 integration/\n\u2502   \u251c\u2500\u2500 test_agent_flow.py\n\u2502   \u251c\u2500\u2500 test_bigquery_connector.py\n\u2502   \u2514\u2500\u2500 test_api_endpoints.py\n\u2514\u2500\u2500 conftest.py  # Shared fixtures\n```\n\n## conftest.py fixtures\n- sample_ad_data\n- mock_agent_response\n- test_client (FastAPI TestClient)",
  "labels": [
    "scaffolding",
    "testing"
  ],
  "created": "2026-01-31T08:00:00Z",
  "updated": "2026-01-31T08:00:00Z",
  "parent": "HALO-1",
  "closedAt": "2026-02-01T05:05:56.247134",
  "comments": [
    {
      "author": "recovery-sync",
      "date": "2026-02-01T05:05:56.247136",
      "text": "Closed by recovery sync: pytest setup complete - 51+ tests running"
    }
  ]
}